PyMemDump/__init__.py
PyMemDump/__main__.py
PyMemDump/core.py
PyMemDump/exceptions.py
PyMemDump/exec_hook.py
PyMemDump/i18n.py
PyMemDump/kernelCore.py
PyMemDump/structs.py
PyMemDump/extensions/__init__.py
PyMemDump/extensions/abstract.py
PyMemDump/functional/__init__.py
PyMemDump/functional/mem_operate.py
PyMemDump/functional/mem_search.py
PyMemDump/res/__init__.py
PyMemDump/res/lang.json
PyMemDump/utils/__init__.py
PyMemDump/utils/_auto_language.py
PyMemDump/utils/_decorator_base.py
PyMemDump/utils/_logger.py
PyMemDump/utils/_rich_conv.py
PyMemDump/utils/_types.py
PyMemDump/utils/constants.py
PyMemDump/utils/decorators.py
PyMemDump/utils/help_beautiful.py
PyMemDump/utils/mem_progress.py
PyMemDump/utils/utils.py
pymemdump-0.2.1.post7.dist-info/licenses/LICENSE
pymemdump-0.2.1.post7.dist-info/METADATA
pymemdump-0.2.1.post7.dist-info/WHEEL
pymemdump-0.2.1.post7.dist-info/top_level.txt
pymemdump-0.2.1.post7.dist-info/RECORD
