Metadata-Version: 2.4
Name: PyMemDump
Version: 0.2.1.post7
Summary: A Python library for memory dumping
Home-page: https://github.com/Fuxuan-CN/PyMemDump
Author: Fuxuan-CN
Author-email: fuxuan001@foxmail.com
License: MIT
Classifier: Programming Language :: Python :: 3
Classifier: License :: OSI Approved :: MIT License
Classifier: Operating System :: OS Independent
Requires: rich
Requires: psutil
License-File: LICENSE
Dynamic: author
Dynamic: author-email
Dynamic: classifier
Dynamic: description
Dynamic: description-content-type
Dynamic: home-page
Dynamic: license
Dynamic: license-file
Dynamic: requires
Dynamic: summary
